ncei_cruise_schema/__init__.py
ncei_cruise_schema/entity/__init__.py
ncei_cruise_schema/entity/access_path.py
ncei_cruise_schema/entity/contact.py
ncei_cruise_schema/entity/dataset.py
ncei_cruise_schema/entity/dataset_instrument_mapping.py
ncei_cruise_schema/entity/dataset_parameter.py
ncei_cruise_schema/entity/dataset_platform_mapping.py
ncei_cruise_schema/entity/dataset_project_mapping.py
ncei_cruise_schema/entity/dataset_scientist_mapping.py
ncei_cruise_schema/entity/dataset_shape_mapping.py
ncei_cruise_schema/entity/dataset_source_mapping.py
ncei_cruise_schema/entity/dataset_survey_mapping.py
ncei_cruise_schema/entity/dataset_type.py
ncei_cruise_schema/entity/file.py
ncei_cruise_schema/entity/file_access_path_mapping.py
ncei_cruise_schema/entity/file_format.py
ncei_cruise_schema/entity/file_parameter.py
ncei_cruise_schema/entity/file_shape_mapping.py
ncei_cruise_schema/entity/file_type.py
ncei_cruise_schema/entity/instrument.py
ncei_cruise_schema/entity/parameter_detail.py
ncei_cruise_schema/entity/platform.py
ncei_cruise_schema/entity/project.py
ncei_cruise_schema/entity/project_parameter.py
ncei_cruise_schema/entity/shape.py
ncei_cruise_schema/entity/survey.py
ncei_cruise_schema/entity/survey_parameter.py
ncei_cruise_schema/entity/survey_shape_mapping.py
ncei_cruise_schema/entity/version_description.py
ncei_cruise_schema/orm/__init__.py
ncei_cruise_schema/orm/column_consts.py
ncei_cruise_schema/orm/cx_oracle.py
ncei_cruise_schema/orm/entity.py
ncei_cruise_schema/orm/jdbc.py
ncei_cruise_schema/orm/persistence.py
ncei_cruise_schema/orm/query.py
ncei_cruise_schema/orm/query_pair.py
ci_cmg_cruise_schema_orm-1.1.4.dist-info/LICENSE
ci_cmg_cruise_schema_orm-1.1.4.dist-info/METADATA
ci_cmg_cruise_schema_orm-1.1.4.dist-info/WHEEL
ci_cmg_cruise_schema_orm-1.1.4.dist-info/top_level.txt
ci_cmg_cruise_schema_orm-1.1.4.dist-info/RECORD
