Metadata-Version: 2.1
Name: ci-cmg-cruise-schema-orm
Version: 1.1.4
Summary: ORM classes for the cruise schema
Home-page: https://github.com/ci-cmg/cruise-schema-orm-py
License: UNKNOWN
Platform: UNKNOWN
Classifier: Programming Language :: Python :: 2.7
Classifier: Programming Language :: Python :: 3
Classifier: Programming Language :: Python :: Implementation :: CPython
Classifier: Programming Language :: Python :: Implementation :: Jython
Classifier: License :: OSI Approved :: MIT License
Classifier: Operating System :: OS Independent
Requires-Python: >=2.7
License-File: LICENSE
Requires-Dist: JayDeBeApi
Requires-Dist: oracledb
Requires-Dist: future
Requires-Dist: setuptools
